manage_savestates/__init__.py
manage_savestates/advanced_cursor.py
manage_savestates/common.py
manage_savestates/directories.py
manage_savestates/main.py
manage_savestates/settings.py
manage_savestates/scripts/applescript/focus_window.applescript
manage_savestates-1.3.1.dist-info/METADATA
manage_savestates-1.3.1.dist-info/WHEEL
manage_savestates-1.3.1.dist-info/entry_points.txt
manage_savestates-1.3.1.dist-info/licenses/LICENSE
manage_savestates-1.3.1.dist-info/RECORD
