Metadata-Version: 2.1
Name: manage-savestates
Version: 1.3.1
Summary: Manages savestates and macros made with gz
Project-URL: Homepage, https://github.com/pilgrimtabby/manage-savestates
Project-URL: Issues, https://github.com/pilgrimtabby/manage-savestates/issues
Author-email: pilgrim_tabby <pilgrimtabby@gmail.com>
License-File: LICENSE
Classifier: License :: OSI Approved :: BSD License
Classifier: Operating System :: MacOS
Classifier: Operating System :: Microsoft :: Windows
Classifier: Programming Language :: Python :: 3
Requires-Python: >=3.7
Requires-Dist: chime; platform_system != 'Windows'
Requires-Dist: pywin32; platform_system == 'Windows'
